README.md
setup.py
guangmutools/__init__.py
guangmutools/base.py
guangmutools/codecs_trans.py
guangmutools/decorators.py
guangmutools/logger_helper.py
guangmutools/sql_data_collection.py
guangmutools.egg-info/PKG-INFO
guangmutools.egg-info/SOURCES.txt
guangmutools.egg-info/dependency_links.txt
guangmutools.egg-info/requires.txt
guangmutools.egg-info/top_level.txt
guangmutools/cachemgr/__init__.py
guangmutools/cachemgr/redispool_mgr.py
guangmutools/dbutils/__init__.py
guangmutools/dbutils/cachepools.py
guangmutools/dbutils/connection_pool.py
guangmutools/dbutils/graph_db.py
guangmutools/msgqueue/__init__.py
guangmutools/msgqueue/rabbitma_tool.py
tests/__init__.py
tests/test_normal.py
tests/cachemgr/__init__.py
tests/cachemgr/test_redis_pool.py