Metadata-Version: 1.0
Name: guangmutools
Version: 0.66
Summary: collection of some tools for guangmu system
Home-page: https://gitlab.xsjcs.cn/kefu/guangmu/commonutils.git
Author: caimiao
Author-email: caimiao@kingsoft.com
License: MIT Licence
Keywords: helpers,tools,widgets
Platform: any
